{
  "sources": [
    {
      "source": "facebook",
      "url": "https://www.facebook.com/reel/2001631803760371",
      "post": {
        "author": "Story Makers",
        "caption": "Story Makers · FollowStory Makers · Original audioThe old man always sat in Booth Seven.Same diner. Same black coffee. Same quiet stare out the window.The waitresses knew him as Mr. Hale — a white-haired man with a trimmed beard, a worn wooden cane, and the kind of silence that made people lower their voices around him without knowing why.He never caused trouble. He never stayed long. And every Tuesday at exactly noon, he came alone.That was the day the bikers walked in.There were six of them, loud enough to turn the whole diner into their stage. Leather vests, heavy boots, big laughs, bigger egos. Their leader, a giant man named Rex, spotted the old man before he even sat down.Something about quiet dignity always made cruel men itchy.Rex walked over smirking, slapped the edge of the booth, and leaned in.“Well, look at this,” he said. “A king in a diner.”The old man didn’t answer.That only made the others laugh harder.Then Rex did it.He grabbed the old man’s cane and yanked it out of his hand.The table jumped. A glass of water tipped over and shattered on the floor. The diner burst into rough laughter as Rex walked down the aisle swinging the cane like a trophy.“Careful,” one biker shouted. “He might need that!”The old man stayed seated.He didn’t yell. Didn’t beg. Didn’t even look at Rex first.He only looked at the cane lying on the floor after Rex dropped it.Then he looked at the water dripping from the table.Then—very slowly—he looked at Rex’s vest.There, stitched inside the leather collar, almost hidden unless you were close enough to see it, was a faded silver hawk patch.The old man’s expression changed.Not much.Just enough.He slipped one hand into his jacket and pulled out a small black key fob.At first Rex laughed again.“What, old man? Gonna beep me to death?”The old man pressed one button.A soft click.Then he lifted the fob to his ear like he had done it a hundred times before.“It’s me,” he said.The laughter in the diner began to thin.Small pause.“Bring them.”He lowered the fob.Rex smirked, but it didn’t look as strong this time.From outside the diner windows came the sudden scream of tires.Heads turned.Then another.Then another.Three black SUVs slid in hard across the roadside lot, headlights flaring through the glass.The diner went dead silent.The bikers stopped smiling one by one.Doors opened outside.Men in dark suits stepped out fast.The old man finally lifted his eyes to Rex.For the first time, there was no humiliation left in him.Only cold certainty.Rex tried to laugh again, but it came out thin.“What is this?”The old man’s gaze dropped once more to the faded silver hawk stitched inside Rex’s collar.When he spoke, his voice was calm enough to terrify the whole diner.“Because if that patch came from the man I think it did…”He looked straight into Rex’s face.“…then you just stole your grandfather’s cane.”👉 Part 2 in the comments See less ::-webkit-scrollbar { -webkit-appearance: none; width: 7px; } ::-webkit-scrollbar-thumb { border-radius: 4px; background: var(--scroll-thumb); }499K8.6K5.3K885911",
        "article": {
          "source": "fullstory.fun",
          "url": "https://fullstory.fun/2026/04/23/%f0%9f%8e%ac-part-2-the-biker-who-didnt-know-his-real-name/",
          "title": "🎬 PART 2: The Biker Who Didn’t Know His Real Name",
          "content": "Nobody in the diner moved.\n\nNot the waitresses.\nNot the bikers.\nNot even Rex.\n\nThe words seemed too strange to fit in the room.\n\nYour grandfather’s cane.\n\nRex stared at the old man as if he’d misheard him.\n\nThen the diner door opened, and two men in dark suits stepped in with a woman carrying a leather file case. They weren’t cops. They didn’t need to be. The way they walked made the whole room clear itself without being told.\n\nOne of them bent, picked up the cane from the floor, and handed it carefully back to Mr. Hale.\n\nThe old man took it without looking away from Rex.\n\n“What game is this?” Rex asked, but now there was a crack in his voice.\n\nMr. Hale ignored the question.\n\nInstead, he said, “Take off the vest.”\n\nRex’s shoulders tightened instantly.\n\n“No.”\n\nOne of the bikers behind him muttered, “Rex…”\n\nThe old man gave the smallest nod toward the woman with the file.\n\nShe opened it and pulled out a photograph.\n\nThen she placed it on the table.\n\nIt showed a young man in a leather vest, standing beside a motorcycle, smiling recklessly at the camera.\n\nOn the inside of his collar was the same faded silver hawk patch.\n\nRex looked down at it.\n\nThen froze.\n\nBecause the man in the picture had his eyes.\n\nHis jawline.\n\nHis exact crooked half-smile.\n\nThe old man finally spoke again.\n\n“His name was Ethan Hale. He was my son.”\n\nThe whole diner stayed silent.\n\nRex didn’t blink.\n\n“My mother told me my father was dead,” he said quietly.\n\nMr. Hale’s face tightened.\n\n“He is,” he said. “For twenty-two years.”\n\nRex swallowed hard.\n\n“Then how do you know me?”\n\nThe old man rested both hands on the cane and answered like it cost him something to breathe.\n\n“Because Ethan vanished before he could bring you home.”\n\nThe woman beside him opened the file again and slid out a second photograph — this one older, worn at the corners. A younger Ethan stood beside a pregnant woman outside a trailer with one hand protectively over her belly.\n\nRex’s face went pale.\n\nThat was his mother.\n\n“I hired people to search for him for years,” Mr. Hale said. “But your mother ran after Ethan was killed. She thought I blamed her for taking him away from the family. I didn’t.” His voice roughened. “I just never found her.”\n\nRex stared at the photographs like they were moving under his eyes.\n\nThe whole diner, the leather, the tough act, the laughter — all of it suddenly looked thin.\n\n“My mom…” he began, then stopped. “She died last winter.”\n\nThe old man closed his eyes for one second.\n\nWhen he opened them, they were wet.\n\n“She kept you from me because she was scared,” he said. “And I stayed away too long because I was proud.” Then he looked at Rex with brutal honesty. “We both failed you.”\n\nThat hit harder than a shout ever could.\n\nOne of the bikers in the back slowly sank into a booth, speechless.\n\nRex looked down at the silver hawk patch on his vest.\n\n“My mother sewed that back on every time it tore,” he said. “She told me it was the only thing my father left me.”\n\nMr. Hale reached into his coat and pulled out a small metal tin. Inside was an identical patch — old, faded, preserved for years.\n\n“Your grandmother made them,” he said. “One for Ethan. One to keep at home.” His voice broke. “I never thought I’d see the other one again.”\n\nRex’s face changed then.\n\nThe arrogance was gone.\n\nThe mockery was gone.\n\nHe suddenly looked much younger than the giant biker everyone had been afraid of.\n\nMore like a lost boy wearing too much leather.\n\nHe looked at the cane in Mr. Hale’s hands.\n\nThen at the broken glass on the floor.\n\nThen at the old man himself.\n\n“I didn’t know,” he said.\n\nMr. Hale nodded slowly.\n\n“I know.”\n\nRex took one step forward.\n\nThe other bikers didn’t laugh this time.\n\nNo one did.\n\nHe bent down, picked up the old man’s spilled napkin from the table, then looked ashamed of how small that gesture was compared to what he had done.\n\n“I’m sorry,” he said, and his voice was no longer cocky at all. “I thought you were just some old man.”\n\nMr. Hale gave a sad half-smile.\n\n“I was,” he said. “Until I saw my son in your face.”\n\nThat destroyed whatever was left of Rex’s control.\n\nHis eyes filled.\n\nHe tore off the leather vest, looked at the silver hawk patch stitched inside, and for the first time in his life understood why his mother had cried whenever she touched it.\n\n“My real name isn’t Rex, is it?” he asked.\n\nMr. Hale’s grip tightened on the cane.\n\n“No,” he said softly. “Your name is Eli Hale. Ethan named you before you were born.”\n\nRex — Eli — let out a broken breath and sat down hard in the empty diner booth across from him, like his legs no longer trusted the floor.\n\nFor a long second, grandfather and grandson just looked at each other across the same table where humiliation had started minutes earlier.\n\nThen Eli whispered the question that had been missing from his whole life:\n\n“Did he want me?”\n\nMr. Hale answered instantly.\n\n“With everything he had.”\n\nSilence again.\n\nBut this time it wasn’t cruel.\n\nIt was full.\n\nMr. Hale slowly held out the cane.\n\nEli looked confused.\n\nThe old man’s voice shook.\n\n“Help me up.”\n\nEli stood at once, stepped forward, and carefully placed the cane into his grandfather’s hand.\n\nThen, just as carefully, he offered his arm.\n\nThe old man took it.\n\nAnd in the middle of that roadside diner, with shattered glass still on the floor and black SUVs waiting outside, the biker who had walked in laughing helped his grandfather stand—\n\nnot because he was ordered to,\n\nbut because blood had finally found blood.",
          "publishedAt": "2026-04-23T14:32:38+00:00",
          "modifiedAt": null,
          "image": "https://fullstory.fun/wp-content/uploads/2026/04/sdvzdv.png"
        },
        "timeText": null,
        "timeDetail": null,
        "timeUrl": "https://www.facebook.com/reel/2001631803760371",
        "media": [
          {
            "type": "video",
            "url": "https://scontent.fdad3-6.fna.fbcdn.net/o1/v/t2/f2/m366/AQPf54eE7_CoubPX503AEgEKUjr6yYGVMr8r1ReiQSrVNmHUecPrSPNloZmPM6in6A3MXfhZXZ8dz766_HAmh97amTBgf4aacZy1Ssn7f0aFVA.mp4?_nc_cat=102&_nc_oc=AdoEYtFiPN6HEHnepRJVRGRJMAxR62-O8PtG0raUdklF5XoqUQy1JRFCyFXd4N4TXJ4&_nc_sid=5e9851&_nc_ht=scontent.fdad3-6.fna.fbcdn.net&_nc_ohc=W7D53Y7LLfsQ7kNvwHSmigG&efg=eyJ2ZW5jb2RlX3RhZyI6Inhwdl9wcm9ncmVzc2l2ZS5GQUNFQk9PSy4uQzMuNzIwLmRhc2hfaDI2NC1iYXNpYy1nZW4yXzcyMHAiLCJ4cHZfYXNzZXRfaWQiOjE0NzMxNjE0MjA4NTY0ODUsImFzc2V0X2FnZV9kYXlzIjo4MSwidmlfdXNlY2FzZV9pZCI6MTAxMjIsImR1cmF0aW9uX3MiOjE1LCJ1cmxnZW5fc291cmNlIjoid3d3In0%3D&ccb=17-1&vs=c8cebfabcf40f49&_nc_vs=HBksFQIYRWZiX2VwaGVtZXJhbC8wMDRBNTQyMTg5MTNGREY1MDRFOENBQkQyNUFBNzY5MV9tdF8xX3ZpZGVvX2Rhc2hpbml0Lm1wNBUAAsgBEgAVAhhAZmJfcGVybWFuZW50LzgyNDdCNTBCRjlFMEI3Qzk1MTZEMTc1QzE3ODBFMjlGX2F1ZGlvX2Rhc2hpbml0Lm1wNBUCAsgBEgAoABgAGwKIB3VzZV9vaWwBMRJwcm9ncmVzc2l2ZV9yZWNpcGUBMRUAACbK8v7yo_WdBRUCKAJDMywXQC4U_fO2RaIYGWRhc2hfaDI2NC1iYXNpYy1nZW4yXzcyMHARAHUCZZSeAQA&_nc_gid=JVPVFUXt89jpef-Qffp-XA&_nc_ss=7c2a8&_nc_zt=28&oh=00_AQD3zX3PQyWUzQNMdKfxiay_AphFaqtGe0JEQOV4GZWghA&oe=6A5C2636&bitrate=1330463&tag=dash_h264-basic-gen2_720p"
          }
        ]
      },
      "engagement": {
        "likes": null,
        "comments": null,
        "shares": null
      },
      "comments": [
        {
          "author": "Story Makers",
          "isAuthor": true,
          "type": "comment",
          "replyTo": null,
          "text": "· · Next Episode https://fullstory.fun/.../%f0%9f%8e%ac-part-2-the-biker.../",
          "links": [
            {
              "text": "https://fullstory.fun/.../%f0%9f%8e%ac-part-2-the-biker.../",
              "url": "https://fullstory.fun/2026/04/23/%f0%9f%8e%ac-part-2-the-biker-who-didnt-know-his-real-name/?fbclid=IwZXh0bgNhZW0CMTAAYnJpZBExUGdZTUdERkoxUHY0RUk2cXNydGMGYXBwX2lkEDIyMjAzOTE3ODgyMDA4OTIAAR6VPNap19jlLfU5p4NhmxBpW_4h3mGSyu9vnF1HW_oVfsa9dNiMhUm1XoG9mw_aem_p_khsQeuAHqAYxJ-vn9zyw"
            }
          ],
          "timeText": "11w",
          "timeDetail": "Thursday, April 23, 2026 at 9:32 PM",
          "timeUrl": "https://www.facebook.com/reel/2001631803760371/?comment_id=850071871470141",
          "label": "Comment by Story Makers 11 weeks ago",
          "replies": []
        },
        {
          "author": "Christopher Ohlsen",
          "isAuthor": false,
          "type": "comment",
          "replyTo": null,
          "text": "· Real bikers would’ve never done that, they would’ve sat with him and bought him a cup of coffee!",
          "links": [],
          "timeText": "11w",
          "timeDetail": "Friday, April 24, 2026 at 4:08 AM",
          "timeUrl": "https://www.facebook.com/reel/2001631803760371/?comment_id=808424612335308",
          "label": "Comment by Christopher Ohlsen 11 weeks ago",
          "replies": []
        },
        {
          "author": "Susan Ginn",
          "isAuthor": false,
          "type": "comment",
          "replyTo": null,
          "text": "· Bikers are gentle. The truth would of been for them to buy his breakfast.",
          "links": [],
          "timeText": "11w",
          "timeDetail": "Friday, April 24, 2026 at 4:12 AM",
          "timeUrl": "https://www.facebook.com/reel/2001631803760371/?comment_id=847476657645531",
          "label": "Comment by Susan Ginn 11 weeks ago",
          "replies": []
        },
        {
          "author": "Nigel Page",
          "isAuthor": false,
          "type": "comment",
          "replyTo": null,
          "text": "· Look carefully 3 different walking sticks",
          "links": [],
          "timeText": "11w",
          "timeDetail": "Friday, April 24, 2026 at 3:18 AM",
          "timeUrl": "https://www.facebook.com/reel/2001631803760371/?comment_id=1002723815431927",
          "label": "Comment by Nigel Page 11 weeks ago",
          "replies": []
        },
        {
          "author": "Lyn Lyn",
          "isAuthor": false,
          "type": "comment",
          "replyTo": null,
          "text": "· Bring them! The cavalry has arrived",
          "links": [],
          "timeText": "11w",
          "timeDetail": "Friday, April 24, 2026 at 5:42 AM",
          "timeUrl": "https://www.facebook.com/reel/2001631803760371/?comment_id=1884679412075087",
          "label": "Comment by Lyn Lyn 11 weeks ago",
          "replies": []
        },
        {
          "author": "Eileen Meighan",
          "isAuthor": false,
          "type": "comment",
          "replyTo": null,
          "text": "· Bikers definitely don't behave like this....",
          "links": [],
          "timeText": "11w",
          "timeDetail": "Friday, April 24, 2026 at 3:48 AM",
          "timeUrl": "https://www.facebook.com/reel/2001631803760371/?comment_id=1671376147618693",
          "label": "Comment by Eileen Meighan 11 weeks ago",
          "replies": []
        }
      ],
      "warnings": [
        "post_time_missing: post time link was not found"
      ],
      "scrapedAt": "2026-07-14T13:29:56.583Z"
    }
  ]
}